aiosnzbd/__init__.py
aiosnzbd/bound_methods.py
aiosnzbd/exception.py
aiosnzbd/job_functions.py
aiosnzbd/requests.py
aiosnzbd-0.1.0.dist-info/LICENSE
aiosnzbd-0.1.0.dist-info/METADATA
aiosnzbd-0.1.0.dist-info/WHEEL
aiosnzbd-0.1.0.dist-info/top_level.txt
aiosnzbd-0.1.0.dist-info/RECORD
