Metadata-Version: 2.2
Name: aiosnzbd
Version: 0.1.0
Summary: Complete Asynchronous API wrapper for the usenet downloading tool SABnzbd
Author: Andrews Jack
Author-email: 
License: MIT
Keywords: sabnzbd async client api wrapper
Classifier: Programming Language :: Python :: 3
Classifier: License :: OSI Approved :: MIT License
Classifier: Operating System :: OS Independent
Requires-Python: >=3.9
License-File: LICENSE
Requires-Dist: httpx
Requires-Dist: urllib3
Dynamic: author
Dynamic: classifier
Dynamic: description
Dynamic: description-content-type
Dynamic: keywords
Dynamic: license
Dynamic: requires-dist
Dynamic: requires-python
Dynamic: summary
